Bother-1.1.data/scripts/bother
bother_utils/__init__.py
bother_utils/heightmap.py
bother_utils/srtm.py
Bother-1.1.dist-info/LICENSE
Bother-1.1.dist-info/METADATA
Bother-1.1.dist-info/WHEEL
Bother-1.1.dist-info/top_level.txt
Bother-1.1.dist-info/RECORD
