Metadata-Version: 2.1
Name: Bother
Version: 1.1
Summary: A script to produce heightmaps (primarily for OpenTTD) using real-world elevation data.
Home-page: https://github.com/bunburya/bother
Author: bunburya
Author-email: 
Keywords: srtm elevation heightmap openttd
Classifier: Programming Language :: Python :: 3
Classifier: License :: OSI Approved :: MIT License
License-File: LICENSE
Requires-Dist: numpy
Requires-Dist: rasterio
Requires-Dist: pillow
Requires-Dist: requests
Requires-Dist: appdirs
Requires-Dist: tqdm
